dagster_shell/__init__.py
dagster_shell/solids.py
dagster_shell/utils.py
dagster_shell/version.py
dagster_shell-1.0.5.dist-info/LICENSE
dagster_shell-1.0.5.dist-info/METADATA
dagster_shell-1.0.5.dist-info/WHEEL
dagster_shell-1.0.5.dist-info/top_level.txt
dagster_shell-1.0.5.dist-info/RECORD
