Metadata-Version: 2.1
Name: dagster-shell
Version: 1.0.5
Summary: Package for Dagster shell ops.
Home-page: https://github.com/dagster-io/dagster/tree/master/python_modules/libraries/dagster-shell
Author: Elementl
Author-email: hello@elementl.com
License: Apache-2.0
Platform: UNKNOWN
Classifier: Programming Language :: Python :: 3.7
Classifier: Programming Language :: Python :: 3.8
Classifier: Programming Language :: Python :: 3.9
Classifier: Programming Language :: Python :: 3.10
Classifier: License :: OSI Approved :: Apache Software License
Classifier: Operating System :: OS Independent
License-File: LICENSE
Requires-Dist: dagster (==1.0.5)
Provides-Extra: test
Requires-Dist: psutil ; extra == 'test'
